deployment/__init__.py
deployment/app.py
deployment/speech_inference.py
deployment/speech_inference_cli.py
deployment/transcription_model.py
deployment/faster_whisper/__init__.py
deployment/faster_whisper/alignment.py
deployment/faster_whisper/asr.py
deployment/faster_whisper/audio.py
deployment/faster_whisper/diarize.py
deployment/faster_whisper/load_asr_model.py
deployment/faster_whisper/mel_filters.npz
deployment/faster_whisper/subtitles_processor.py
deployment/faster_whisper/types.py
deployment/faster_whisper/utils.py
deployment/faster_whisper/vad.py
training/__init__.py
training/audio_data_processor.py
training/collator.py
training/data_prep.py
training/evaluation.py
training/load_data.py
training/main.py
training/merge_lora.py
training/model_trainer.py
training/wandb_callback.py
training/whisper_model_prep.py
africanwhisper-0.9.23.dist-info/LICENSE
africanwhisper-0.9.23.dist-info/METADATA
africanwhisper-0.9.23.dist-info/WHEEL
africanwhisper-0.9.23.dist-info/top_level.txt
africanwhisper-0.9.23.dist-info/RECORD
